nl2sql360/__init__.py
nl2sql360/arguments/__init__.py
nl2sql360/arguments/core_args.py
nl2sql360/arguments/dataset_args.py
nl2sql360/arguments/delete_history_args.py
nl2sql360/arguments/evaluation_args.py
nl2sql360/arguments/hf_argparser.py
nl2sql360/arguments/parser.py
nl2sql360/arguments/report_args.py
nl2sql360/cli/__init__.py
nl2sql360/cli/cli.py
nl2sql360/cli/util.py
nl2sql360/core/__init__.py
nl2sql360/core/core.py
nl2sql360/database/__init__.py
nl2sql360/database/model.py
nl2sql360/database/template.py
nl2sql360/database/util.py
nl2sql360/dataset/__init__.py
nl2sql360/dataset/dataset.py
nl2sql360/evaluator/__init__.py
nl2sql360/evaluator/bird_accuracy.py
nl2sql360/evaluator/bird_ex.py
nl2sql360/evaluator/f1.py
nl2sql360/evaluator/rves.py
nl2sql360/evaluator/spider_accuracy.py
nl2sql360/evaluator/spider_ex_em.py
nl2sql360/evaluator/ves.py
nl2sql360/evaluator/bird_eval/__init__.py
nl2sql360/evaluator/bird_eval/bird_accuracy.py
nl2sql360/evaluator/bird_eval/bird_ex.py
nl2sql360/evaluator/bird_eval/bird_rves.py
nl2sql360/evaluator/bird_eval/bird_ves.py
nl2sql360/evaluator/bird_eval/evaluation_f1.py
nl2sql360/evaluator/bird_eval/evaluation_utils.py
nl2sql360/evaluator/test_suite_sql_eval/__init__.py
nl2sql360/evaluator/test_suite_sql_eval/evaluation.py
nl2sql360/evaluator/test_suite_sql_eval/exec_eval.py
nl2sql360/evaluator/test_suite_sql_eval/parse.py
nl2sql360/evaluator/test_suite_sql_eval/process_sql.py
nl2sql360/filter/__init__.py
nl2sql360/filter/filter.py
nl2sql360/parser/__init__.py
nl2sql360/parser/sql_parser.py
nl2sql360-1.1.0.dist-info/LICENSE
nl2sql360-1.1.0.dist-info/METADATA
nl2sql360-1.1.0.dist-info/WHEEL
nl2sql360-1.1.0.dist-info/entry_points.txt
nl2sql360-1.1.0.dist-info/top_level.txt
nl2sql360-1.1.0.dist-info/RECORD
