Metadata-Version: 2.1
Name: nl2sql360
Version: 1.1.0
Summary: A Multi-angle NL2SQL Evaluation Framework
Home-page: https://github.com/HKUSTDial/NL2SQL360
Author: boyanli
Author-email: boyanli@hkust-gz.edu.cn
License: MIT License
Keywords: NL2SQL,Text-to-SQL,T2S,SQL,Database,NLIDB
Classifier: Development Status :: 3 - Alpha
Classifier: Intended Audience :: Developers
Classifier: Intended Audience :: Education
Classifier: Intended Audience :: Science/Research
Classifier: License :: OSI Approved :: MIT License
Classifier: Operating System :: OS Independent
Classifier: Programming Language :: Python :: 3
Classifier: Programming Language :: Python :: 3.8
Classifier: Programming Language :: Python :: 3.9
Classifier: Programming Language :: Python :: 3.10
Classifier: Programming Language :: Python :: 3.11
Classifier: Topic :: Database
Classifier: Topic :: Scientific/Engineering :: Artificial Intelligence
Classifier: Topic :: Software Development :: Testing
Requires-Python: >=3.8.0
License-File: LICENSE
Requires-Dist: psycopg2-binary
Requires-Dist: pymysql
Requires-Dist: func-timeout
Requires-Dist: pydantic
Requires-Dist: sqlglot[rs]
Requires-Dist: tqdm
Requires-Dist: loguru
Requires-Dist: sqlalchemy
Requires-Dist: pandas
